pyEthOS/__init__.py
pyEthOS/exceptions.py
pyEthOS/pyEthOS.py
pyEthOS/utils.py
pyEthOS-1.4.1.dist-info/DESCRIPTION.rst
pyEthOS-1.4.1.dist-info/METADATA
pyEthOS-1.4.1.dist-info/RECORD
pyEthOS-1.4.1.dist-info/WHEEL
pyEthOS-1.4.1.dist-info/metadata.json
pyEthOS-1.4.1.dist-info/top_level.txt
