Metadata-Version: 2.0
Name: pyEthOS
Version: 1.4.1
Summary: Python 2 and 3 interface to the EthOS custom Dashboard API
Home-page: https://github.com/DEKHTIARJonathan/pyEthOS
Author: Jonathan Dekhtiar
Author-email: contact@jonathandekhtiar.eu
License: GPLv3
Keywords: EthOS Etherium Bitcoin Cryptocurrencies API python python3 python2
Platform: UNKNOWN
Classifier: Development Status :: 5 - Production/Stable
Classifier: Environment :: Console
Classifier: Intended Audience :: Developers
Classifier: License :: OSI Approved :: GNU Affero General Public License v3 
Classifier: Operating System :: OS Independent
Classifier: Programming Language :: Python :: 2
Classifier: Programming Language :: Python :: 2.7
Classifier: Programming Language :: Python :: 3
Classifier: Programming Language :: Python :: 3.4
Classifier: Programming Language :: Python :: 3.5
Classifier: Programming Language :: Python :: 3.6
Classifier: Natural Language :: English
Requires-Dist: future (>=0.16.0)
Requires-Dist: requests (>=2.18.1)
Requires-Dist: validators (>=0.12.0)
